Products.CMFBibliographyAT-1.2.1-py2.7-nspkg.pth
Products/CMFBibliographyAT/DuplicatesCriteria.py
Products/CMFBibliographyAT/__init__.py
Products/CMFBibliographyAT/bibapi.py
Products/CMFBibliographyAT/bibliography_tool.png
Products/CMFBibliographyAT/config.py
Products/CMFBibliographyAT/configure.zcml
Products/CMFBibliographyAT/configure.zcml.five
Products/CMFBibliographyAT/events.py
Products/CMFBibliographyAT/interfaces.py
Products/CMFBibliographyAT/marshall.py
Products/CMFBibliographyAT/permissions.py
Products/CMFBibliographyAT/profiles.zcml
Products/CMFBibliographyAT/refresh.txt
Products/CMFBibliographyAT/setuphandlers.py
Products/CMFBibliographyAT/testing.py
Products/CMFBibliographyAT/utils.py
Products/CMFBibliographyAT/version.txt
Products/CMFBibliographyAT/vocabularies.py
Products/CMFBibliographyAT/adapters/__init__.py
Products/CMFBibliographyAT/adapters/bibauthormember.py
Products/CMFBibliographyAT/adapters/configure.zcml
Products/CMFBibliographyAT/adapters/export.py
Products/CMFBibliographyAT/bin/cleanUpCode.py
Products/CMFBibliographyAT/bin/isDirtyCode.py
Products/CMFBibliographyAT/browser/__init__.py
Products/CMFBibliographyAT/browser/configure.zcml
Products/CMFBibliographyAT/browser/export.py
Products/CMFBibliographyAT/browser/import.pt
Products/CMFBibliographyAT/browser/import.py
Products/CMFBibliographyAT/browser/listitemformatter.pt
Products/CMFBibliographyAT/browser/listitemformatter.py
Products/CMFBibliographyAT/content/__init__.py
Products/CMFBibliographyAT/content/article.py
Products/CMFBibliographyAT/content/base.py
Products/CMFBibliographyAT/content/book.py
Products/CMFBibliographyAT/content/booklet.py
Products/CMFBibliographyAT/content/conference.py
Products/CMFBibliographyAT/content/fields.py
Products/CMFBibliographyAT/content/folder.py
Products/CMFBibliographyAT/content/inbook.py
Products/CMFBibliographyAT/content/incollection.py
Products/CMFBibliographyAT/content/inproceedings.py
Products.CMFBibliographyAT-1.2.1.dist-info/DESCRIPTION.rst
Products.CMFBibliographyAT-1.2.1.dist-info/METADATA
Products.CMFBibliographyAT-1.2.1.dist-info/RECORD
Products.CMFBibliographyAT-1.2.1.dist-info/WHEEL
Products.CMFBibliographyAT-1.2.1.dist-info/entry_points.txt
Products.CMFBibliographyAT-1.2.1.dist-info/metadata.json
Products.CMFBibliographyAT-1.2.1.dist-info/namespace_packages.txt
Products.CMFBibliographyAT-1.2.1.dist-info/top_level.txt
