Metadata-Version: 2.0
Name: Products.CMFBibliographyAT
Version: 1.2.1
Summary: Bibliographic references in Plone
Home-page: http://pypi.python.org/pypi/Products.CMFBibliographyAT
Author: Andreas Jung
Author-email: info@zopyx.com
License: GPL
Keywords: web application server zope zope2 cmf plone bibliography
Platform: UNKNOWN
Classifier: Framework :: Plone
Classifier: Framework :: Zope2
Classifier: Framework :: Zope3
Classifier: Programming Language :: Python
Classifier: Topic :: Software Development :: Libraries :: Python Modules
Requires-Dist: Products.ATExtensions
Requires-Dist: bibliograph.core
Requires-Dist: bibliograph.parsing
Requires-Dist: bibliograph.rendering
Requires-Dist: pyisbn
Requires-Dist: setuptools
Requires-Dist: zope.app.schema
